mehr/__init__.py
mehr/analysis/mifs.py
mehr/optim/__init__.py
mehr/stream/AccessMode.py
mehr/stream/EncodingMode.py
mehr/stream/StreamProgressWrapper.py
mehr/stream/__init__.py
mehr-0.1.dist-info/LICENSE
mehr-0.1.dist-info/LICENSE.txt
mehr-0.1.dist-info/WHEEL
mehr-0.1.dist-info/METADATA
mehr-0.1.dist-info/RECORD
