Metadata-Version: 2.1
Name: mehr
Version: 0.1
Summary: A package with lots of tiny utility additions.
Author-email: Robert Bock <robertbock.98@googlemail.com>
Classifier: License :: OSI Approved :: GNU General Public License v3 or later (GPLv3+)
Project-URL: Home, https://github.com/Moraxno/py-mehr
